test.py
ca_vntl_helper/__init__.py
ca_vntl_helper/decorator.py
ca_vntl_helper-1.1.6.dist-info/LICENSE
ca_vntl_helper-1.1.6.dist-info/METADATA
ca_vntl_helper-1.1.6.dist-info/WHEEL
ca_vntl_helper-1.1.6.dist-info/top_level.txt
ca_vntl_helper-1.1.6.dist-info/RECORD
